win32_vcwin/__init__.py
win32_vcwin/main.py
win32_vcwin/vcwin_worker.exe
win32_vcwin-0.1.0.dist-info/LICENSE
win32_vcwin-0.1.0.dist-info/METADATA
win32_vcwin-0.1.0.dist-info/WHEEL
win32_vcwin-0.1.0.dist-info/entry_points.txt
win32_vcwin-0.1.0.dist-info/top_level.txt
win32_vcwin-0.1.0.dist-info/RECORD
