Metadata-Version: 2.1
Name: win32-vcwin
Version: 0.1.0
Summary: win32-vcwin is a command-line tool for Windows developers to inspect, install, uninstall, and manage components such as Visual C++ Tools, Windows SDK, WDK, and DirectX SDK.
Author: AleirJDawn
Author-email: 
Classifier: Programming Language :: Python :: 3
Classifier: License :: OSI Approved :: MIT License
Requires-Python: >=3.6
License-File: LICENSE
